nextera_py/__init__.py
nextera_py/good_builtins/__init__.py
nextera_py/good_builtins/strings.py
nextera_py/modules/__init__.py
nextera_py-0.0.2.dist-info/licenses/LICENSE
nextera_py-0.0.2.dist-info/METADATA
nextera_py-0.0.2.dist-info/WHEEL
nextera_py-0.0.2.dist-info/top_level.txt
nextera_py-0.0.2.dist-info/RECORD
