Metadata-Version: 2.4
Name: nextera-py
Version: 0.0.2
Summary: A small example package
Author: zengzirui
License-Expression: MIT
Project-URL: Homepage, https://github.com/zengzirui/nextera-py
Project-URL: Issues, https://github.com/zengzirui/nextera-py/issues
Classifier: Programming Language :: Python :: 3
Classifier: Operating System :: OS Independent
Requires-Python: >=3.9
License-File: LICENSE
Dynamic: license-file
